LICENSE.txt
README.md
setup.py
llnb/__init__.py
llnb.egg-info/PKG-INFO
llnb.egg-info/SOURCES.txt
llnb.egg-info/dependency_links.txt
llnb.egg-info/top_level.txt